batchscanner/__init__.py
batchscanner/__main__.py
batchscanner/batchscan.py
batchscanner/config.toml
batchscanner/credentials.py
batchscanner/network.txt
batchscanner/script.txt
batchscanner/sikcli.py
batchscanner/sikcommander.py
batchscanner/sikssh_config.toml
batchscanner/parsers/__init__.py
batchscanner/parsers/parse_show_eh.py
batchscanner/parsers/parse_show_tg.py
batchscanner_siklu-0.1.7.dist-info/LICENCE
batchscanner_siklu-0.1.7.dist-info/METADATA
batchscanner_siklu-0.1.7.dist-info/WHEEL
batchscanner_siklu-0.1.7.dist-info/entry_points.txt
batchscanner_siklu-0.1.7.dist-info/top_level.txt
batchscanner_siklu-0.1.7.dist-info/RECORD
